rtl/alu.v
module alu(
    input [31:0] a,
    input [31:0] b,
    input [3:0] alu_ctrl,
    output reg [31:0] result,
    output zero
);

assign zero = (result == 32'b0);

always @(*) begin
    case (alu_ctrl)
        4'b0000: result = a + b;
        4'b0001: result = a - b;
        4'b0010: result = a & b;
        4'b0011: result = a | b;
        4'b0100: result = a ^ b;
        4'b0101: result = ($signed(a) < $signed(b)) ? 32'd1 : 32'd0;
        4'b0110: result = a << b[4:0];
        4'b0111: result = a >> b[4:0];
        4'b1000: result = $signed(a) >>> b[4:0];
        default: result = 32'b0;
    endcase
end

endmodule

tb/alu_tb.v
`timescale 1ns/1ps

module alu_tb;

    reg  [31:0] a, b;
    reg  [3:0]  alu_ctrl;
    wire [31:0] result;
    wire        zero;

    alu uut (
        .a(a),
        .b(b),
        .alu_ctrl(alu_ctrl),
        .result(result),
        .zero(zero)
    );

    initial begin
        $dumpfile("alu.vcd");
        $dumpvars(0, alu_tb);

        a = 32'd10; b = 32'd5; alu_ctrl = 4'b0000;
        #10; $display("ADD: %0d + %0d = %0d", a, b, result);

        a = 32'd10; b = 32'd5; alu_ctrl = 4'b0001;
        #10; $display("SUB: %0d - %0d = %0d", a, b, result);

        a = 32'hF0; b = 32'hFF; alu_ctrl = 4'b0010;
        #10; $display("AND: %h & %h = %h", a, b, result);

        a = 32'hF0; b = 32'hF; alu_ctrl = 4'b0011;
        #10; $display("OR:  %h | %h = %h", a, b, result);

        a = 32'hFF; b = 32'hFF; alu_ctrl = 4'b0100;
        #10; $display("XOR: %h ^ %h = %h", a, b, result);

        a = 32'd3; b = 32'd5; alu_ctrl = 4'b0101;
        #10; $display("SLT: %0d < %0d = %0d", a, b, result);

        a = 32'd1; b = 32'd4; alu_ctrl = 4'b0110;
        #10; $display("SLL: %0d << %0d = %0d", a, b, result);

        a = 32'd16; b = 32'd2; alu_ctrl = 4'b0111;
        #10; $display("SRL: %0d >> %0d = %0d", a, b, result);

        a = -32'd8; b = 32'd1; alu_ctrl = 4'b1000;
        #10; $display("SRA: -8 >>> 1 = %0d", $signed(result));

        a = 32'd5; b = 32'd5; alu_ctrl = 4'b0001;
        #10; $display("ZERO flag: %0d", zero);

        $finish;
    end

endmodule

alu.vcd
$date
	Sun Aug 02 10:53:43 2026
$end
$version
	Icarus Verilog
$end
$timescale
	1ps
$end
$scope module alu_tb $end
$var wire 1 ! zero $end
$var wire 32 " result [31:0] $end
$var reg 32 # a [31:0] $end
$var reg 4 $ alu_ctrl [3:0] $end
$var reg 32 % b [31:0] $end
$scope module uut $end
$var wire 32 & a [31:0] $end
$var wire 4 ' alu_ctrl [3:0] $end
$var wire 32 ( b [31:0] $end
$var wire 1 ! zero $end
$var reg 32 ) result [31:0] $end
$upscope $end
$upscope $end
$enddefinitions $end
$comment Show the parameter values. $end
$dumpall
$end
#0
$dumpvars
b1111 )
b101 (
b0 '
b1010 &
b101 %
b0 $
b1010 #
b1111 "
0!
$end
#10000
b101 "
b101 )
b1 $
b1 '
#20000
b11110000 "
b11110000 )
b10 $
b10 '
b11111111 %
b11111111 (
b11110000 #
b11110000 &
#30000
b11111111 "
b11111111 )
b11 $
b11 '
b1111 %
b1111 (
#40000
1!
b0 "
b0 )
b100 $
b100 '
b11111111 %
b11111111 (
b11111111 #
b11111111 &
#50000
0!
b1 "
b1 )
b101 $
b101 '
b101 %
b101 (
b11 #
b11 &
#60000
b10000 "
b10000 )
b110 $
b110 '
b100 %
b100 (
b1 #
b1 &
#70000
b100 "
b100 )
b111 $
b111 '
b10 %
b10 (
b10000 #
b10000 &
#80000
b11111111111111111111111111111100 "
b11111111111111111111111111111100 )
b1000 $
b1000 '
b1 %
b1 (
b11111111111111111111111111111000 #
b11111111111111111111111111111000 &
#90000
1!
b0 "
b0 )
b1 $
b1 '
b101 %
b101 (
b101 #
b101 &
